tests/__init__.py
tests/schema_dict_test.py
volent/Column.py
volent/Database.py
volent/Field.py
volent/FullTextIndex.py
volent/Model.py
volent/NestedField.py
volent/Relationship.py
volent/ReverseEngineer.py
volent/Schema.py
volent/Trigger.py
volent/UniqueConstraint.py
volent/Volent.py
volent/__init__.py
volent/exceptions.py
volent/data_types/BigInt.py
volent/data_types/Bool.py
volent/data_types/Decimal.py
volent/data_types/EncodedPrimary.py
volent/data_types/Integer.py
volent/data_types/String.py
volent/data_types/TinyInt.py
volent/data_types/TypeBase.py
volent/data_types/__init__.py
volent/mixins/DatabaseConnection.py
volent/mixins/EntityName.py
volent/mixins/MySQLGeneratorMixin.py
volent/mixins/OrderedClass.py
volent/mixins/ReverseEngineerMixin.py
volent/mixins/__init__.py
volent/query/Delete.py
volent/query/Insert.py
volent/query/Query.py
volent/query/QueryParam.py
volent/query/Select.py
volent/query/Update.py
volent/query/WhereClause.py
volent/query/WhereMixin.py
volent/query/__init__.py
volent/settings/__init__.py
volent/settings/control.py
volent/settings/globe.py
volent/settings/types.py
volent/tests/__init__.py
volent/tests/schema_dict_test.py
volent/tests/validators_test.py
volent/validate/CreditCardNumber.py
volent/validate/Email.py
volent/validate/Equal.py
volent/validate/FutureUnixDate.py
volent/validate/GreaterThan.py
volent/validate/IpAddress.py
volent/validate/Length.py
volent/validate/LessThan.py
volent/validate/NoneOf.py
volent/validate/OneOf.py
volent/validate/PastUnixDate.py
volent/validate/PhoneNumber.py
volent/validate/Range.py
volent/validate/Regex.py
volent/validate/SocialSecurityNumber.py
volent/validate/StrongPassword.py
volent/validate/Validator.py
volent/validate/__init__.py
colemen_volent-0.1.8.dist-info/METADATA
colemen_volent-0.1.8.dist-info/WHEEL
colemen_volent-0.1.8.dist-info/top_level.txt
colemen_volent-0.1.8.dist-info/RECORD
