Metadata-Version: 2.1
Name: colemen-volent
Version: 0.1.8
Summary: volent
Author: Colemen Mitchell Atwood
Author-email: <atwoodcolemen@gmail.com>
Keywords: python
Classifier: Development Status :: 3 - Alpha
Classifier: Intended Audience :: Education
Classifier: Programming Language :: Python :: 2
Classifier: Programming Language :: Python :: 3
Classifier: Operating System :: MacOS :: MacOS X
Classifier: Operating System :: Microsoft :: Windows
Requires-Dist: colemen-utils
